salesforce_expense/__init__.py
salesforce_expense/cli.py
salesforce_expense/core.py
salesforce_expense-0.0.4.dist-info/LICENSE
salesforce_expense-0.0.4.dist-info/METADATA
salesforce_expense-0.0.4.dist-info/WHEEL
salesforce_expense-0.0.4.dist-info/entry_points.txt
salesforce_expense-0.0.4.dist-info/top_level.txt
salesforce_expense-0.0.4.dist-info/RECORD
